pytest_pot/__init__.py
pytest_pot/pot.py
pytest_pot-0.2.0.dist-info/LICENSE
pytest_pot-0.2.0.dist-info/METADATA
pytest_pot-0.2.0.dist-info/WHEEL
pytest_pot-0.2.0.dist-info/top_level.txt
pytest_pot-0.2.0.dist-info/RECORD
